{
    "/js/app.js": "/js/app.js?id=ef7f4986b2ff79813e1d",
    "/css/icons.css": "/css/icons.css?id=744b0f7bdf6d437fce01",
    "/css/app.css": "/css/app.css?id=09ba5bf0e081e77f682e",
    "/js/app.js.map": "/js/app.js.map?id=4eb5899301f3a5b54f15",
    "/js/auth.js": "/js/auth.js?id=31338189e96b30a84200",
    "/js/auth.js.map": "/js/auth.js.map?id=60446e844fbc4a665ace",
    "/js/base.js": "/js/base.js?id=4275b70b4323a98170c7",
    "/js/base.js.map": "/js/base.js.map?id=60f20d714f9be24f60ab",
    "/js/dashboard.js": "/js/dashboard.js?id=ae865516041227dcc53c",
    "/js/dashboard.js.map": "/js/dashboard.js.map?id=bea7ab0141713929eb41",
    "/js/framework.js": "/js/framework.js?id=6ec2d460e5df0b5dbd16",
    "/js/framework.js.map": "/js/framework.js.map?id=48e5da28ad4e4b2bf0b7",
    "/js/http-progress.js": "/js/http-progress.js?id=6c0ea805d22095dcea22",
    "/js/http-progress.js.map": "/js/http-progress.js.map?id=cf417025b31cbecc01bd",
    "/js/kitchensink.js": "/js/kitchensink.js?id=4d50b4853445ab4d8c1a",
    "/js/kitchensink.js.map": "/js/kitchensink.js.map?id=ee3ee81d6d159e68a402",
    "/js/test.js": "/js/test.js?id=1b3a4d0f3ef3a43cd8ad",
    "/js/test.js.map": "/js/test.js.map?id=f6be3eb9e47e7d17c950",
    "/js/tokens.js": "/js/tokens.js?id=15b799853d6a78baaf0e",
    "/js/tokens.js.map": "/js/tokens.js.map?id=77e8fcc5691872d0a08b",
    "/js/users.js": "/js/users.js?id=e28fc58540f8de6d70ae",
    "/js/users.js.map": "/js/users.js.map?id=77547c7ba72162d9f2a4"
}
